[
  {
    "filename": "pictures/photogalery/Bia.jpg"
  },
  {
    "filename": "pictures/photogalery/Bia2.jpg"
  },
  {
  "filename": "pictures/photogalery/bia3.jpg"
  },
  {
    "filename": "pictures/photogalery/riso.jpg"
  },
  {
    "filename": "pictures/photogalery/riso2.jpg"
  },
  {
    "filename": "pictures/photogalery/riso3.jpg"
  },
  {
    "filename": "pictures/photogalery/risobia.jpg"
  },
  {
    "filename": "pictures/photogalery/risobia2.jpg"
  },
  {
    "filename": "pictures/photogalery/pexeso (1).jpg"
  },
  {
    "filename": "pictures/photogalery/pexeso (2).jpg"
  },
  {
    "filename": "pictures/photogalery/pexeso (3).jpg"
  },
  {
    "filename": "pictures/photogalery/pexeso (4).jpg"
  },
  {
    "filename": "pictures/photogalery/pexeso (5).jpg"
  }
]